slimit/__init__.py
slimit/ast.py
slimit/lexer.py
slimit/lextab.py
slimit/mangler.py
slimit/minifier.py
slimit/parser.py
slimit/scope.py
slimit/unicode_chars.py
slimit/yacctab.py
slimit/tests/__init__.py
slimit/tests/test_cmd.py
slimit/tests/test_ecmavisitor.py
slimit/tests/test_lexer.py
slimit/tests/test_mangler.py
slimit/tests/test_minifier.py
slimit/tests/test_nodevisitor.py
slimit/tests/test_parser.py
slimit/visitors/__init__.py
slimit/visitors/ecmavisitor.py
slimit/visitors/minvisitor.py
slimit/visitors/nodevisitor.py
slimit/visitors/scopevisitor.py
slimit3k-0.9.0.dist-info/licenses/LICENSE
slimit3k-0.9.0.dist-info/METADATA
slimit3k-0.9.0.dist-info/WHEEL
slimit3k-0.9.0.dist-info/entry_points.txt
slimit3k-0.9.0.dist-info/top_level.txt
slimit3k-0.9.0.dist-info/RECORD
